git_shell/__init__.py
git_shell/main.py
git_shell-0.1.24.dist-info/licenses/LICENSE
git_shell-0.1.24.dist-info/METADATA
git_shell-0.1.24.dist-info/WHEEL
git_shell-0.1.24.dist-info/entry_points.txt
git_shell-0.1.24.dist-info/top_level.txt
git_shell-0.1.24.dist-info/RECORD
