Metadata-Version: 2.4
Name: git-shell
Version: 0.1.24
Summary: A custom git shell with GPG and SSH certificate authorization
Author-email: Justin Ovens <code@gotunix.net>
Maintainer-email: Justin Ovens <code@gotunix.net>
License-Expression: AGPL-3.0
Project-URL: Homepage, https://github.com/gotunix/git-shell
Project-URL: Repository, https://github.com/gotunix/git-shell.git
Classifier: Development Status :: 4 - Beta
Classifier: Intended Audience :: System Administrators
Classifier: Programming Language :: Python :: 3
Classifier: Topic :: Software Development :: Version Control :: Git
Requires-Python: >=3.8
License-File: LICENSE
Dynamic: license-file
